project_work_summary_mcp/__init__.py
project_work_summary_mcp-0.1.0.dist-info/WHEEL
project_work_summary_mcp-0.1.0.dist-info/entry_points.txt
project_work_summary_mcp-0.1.0.dist-info/METADATA
project_work_summary_mcp-0.1.0.dist-info/RECORD
