Metadata-Version: 2.3
Name: project-work-summary-mcp
Version: 0.1.0
Summary: Add your description here
Author: wangwenbin
Author-email: wangwenbin <wangwenbin@gwm.cn>
Requires-Dist: mcp[cli]>=1.13.0
Requires-Python: >=3.13
